boring_logger/__init__.py
boring_logger-0.0.6.dist-info/LICENSE
boring_logger-0.0.6.dist-info/METADATA
boring_logger-0.0.6.dist-info/WHEEL
boring_logger-0.0.6.dist-info/top_level.txt
boring_logger-0.0.6.dist-info/RECORD
